tests/__init__.py
tests/map/__init__.py
tests/map/test_create_map.py
tests/map/test_positions.py
tests/map/test_simulation_data.py
xrayspectrummodeling/__init__.py
xrayspectrummodeling/examples/__init__.py
xrayspectrummodeling/examples/create_SimulationTrainingMapsMM2017_wfFe01_map.py
xrayspectrummodeling/examples/create_map_mm2017_abstract.py
xrayspectrummodeling/examples/create_test_map.py
xrayspectrummodeling/map/__init__.py
xrayspectrummodeling/map/create_map.py
xrayspectrummodeling/map/positions.py
xrayspectrummodeling/map/simulation_data.py
xrayspectrummodeling-0.2.0.dist-info/DESCRIPTION.rst
xrayspectrummodeling-0.2.0.dist-info/METADATA
xrayspectrummodeling-0.2.0.dist-info/RECORD
xrayspectrummodeling-0.2.0.dist-info/WHEEL
xrayspectrummodeling-0.2.0.dist-info/metadata.json
xrayspectrummodeling-0.2.0.dist-info/top_level.txt
