Metadata-Version: 2.0
Name: xrayspectrummodeling
Version: 0.2.0
Summary: Modeling of an X-ray spectrum in EDS detector
Home-page: https://github.com/drix00/xrayspectrummodeling
Author: Hendrix Demers
Author-email: hendrix.demers@mail.mcgill.ca
License: Apache Software License 2.0
Keywords: xrayspectrummodeling
Platform: UNKNOWN
Classifier: Development Status :: 2 - Pre-Alpha
Classifier: Intended Audience :: Developers
Classifier: License :: OSI Approved :: Apache Software License
Classifier: Natural Language :: English
Classifier: Programming Language :: Python :: 2
Classifier: Programming Language :: Python :: 2.6
Classifier: Programming Language :: Python :: 2.7
Classifier: Programming Language :: Python :: 3
Classifier: Programming Language :: Python :: 3.3
Classifier: Programming Language :: Python :: 3.4
Classifier: Programming Language :: Python :: 3.5
Requires-Dist: numpy
Requires-Dist: h5py
Requires-Dist: matplotlib
Requires-Dist: scipy
Requires-Dist: pymcxray
Requires-Dist: pySpectrumFileFormat
